README.rst
setup.py
plenario_stream_kinesis_consumer/__init__.py
plenario_stream_kinesis_consumer/config.py
plenario_stream_kinesis_consumer/helper.py
plenario_stream_kinesis_consumer/logger.py
plenario_stream_kinesis_consumer/worker.py
plenario_stream_kinesis_consumer.egg-info/PKG-INFO
plenario_stream_kinesis_consumer.egg-info/SOURCES.txt
plenario_stream_kinesis_consumer.egg-info/dependency_links.txt
plenario_stream_kinesis_consumer.egg-info/requires.txt
plenario_stream_kinesis_consumer.egg-info/top_level.txt