Metadata-Version: 1.1
Name: plenario-stream-kinesis-consumer
Version: 0.1.2
Summary: A stream consumer of open data for plenar.io
Home-page: https://github.com/UrbanCCD-UChicago/plenario-stream-kinesis-consumer
Author: Jesus Bracho
Author-email: jbrach347@gmail.com
License: UNKNOWN
Download-URL: https://github.com/UrbanCCD-UChicago/plenario-stream-kinesis-consumer/archive/0.1.2.tar.gz
Keywords: open data,kinesis client library,streaming,etl
Platform: UNKNOWN
